odoo/addons/auth_dynamic_groups/README.rst
odoo/addons/auth_dynamic_groups/__init__.py
odoo/addons/auth_dynamic_groups/__manifest__.py
odoo/addons/auth_dynamic_groups/i18n/ar.po
odoo/addons/auth_dynamic_groups/i18n/auth_dynamic_groups.pot
odoo/addons/auth_dynamic_groups/i18n/ca.po
odoo/addons/auth_dynamic_groups/i18n/da.po
odoo/addons/auth_dynamic_groups/i18n/de.po
odoo/addons/auth_dynamic_groups/i18n/el_GR.po
odoo/addons/auth_dynamic_groups/i18n/es.po
odoo/addons/auth_dynamic_groups/i18n/es_ES.po
odoo/addons/auth_dynamic_groups/i18n/fi.po
odoo/addons/auth_dynamic_groups/i18n/fr.po
odoo/addons/auth_dynamic_groups/i18n/fr_CH.po
odoo/addons/auth_dynamic_groups/i18n/hr.po
odoo/addons/auth_dynamic_groups/i18n/hr_HR.po
odoo/addons/auth_dynamic_groups/i18n/it.po
odoo/addons/auth_dynamic_groups/i18n/nl.po
odoo/addons/auth_dynamic_groups/i18n/pt_BR.po
odoo/addons/auth_dynamic_groups/i18n/sl.po
odoo/addons/auth_dynamic_groups/i18n/tr.po
odoo/addons/auth_dynamic_groups/i18n/tr_TR.po
odoo/addons/auth_dynamic_groups/i18n/zh_CN.po
odoo/addons/auth_dynamic_groups/models/__init__.py
odoo/addons/auth_dynamic_groups/models/res_groups.py
odoo/addons/auth_dynamic_groups/models/res_users.py
odoo/addons/auth_dynamic_groups/readme/CONFIGURE.rst
odoo/addons/auth_dynamic_groups/readme/CONTRIBUTORS.rst
odoo/addons/auth_dynamic_groups/readme/CREDITS.rst
odoo/addons/auth_dynamic_groups/readme/DESCRIPTION.rst
odoo/addons/auth_dynamic_groups/readme/USAGE.rst
odoo/addons/auth_dynamic_groups/static/description/icon.png
odoo/addons/auth_dynamic_groups/static/description/index.html
odoo/addons/auth_dynamic_groups/tests/__init__.py
odoo/addons/auth_dynamic_groups/tests/test_auth_dynamic_groups.py
odoo/addons/auth_dynamic_groups/views/res_groups.xml
odoo11_addon_auth_dynamic_groups-11.0.1.0.0.99.dev9.dist-info/METADATA
odoo11_addon_auth_dynamic_groups-11.0.1.0.0.99.dev9.dist-info/WHEEL
odoo11_addon_auth_dynamic_groups-11.0.1.0.0.99.dev9.dist-info/top_level.txt
odoo11_addon_auth_dynamic_groups-11.0.1.0.0.99.dev9.dist-info/RECORD
